file_delete_manager-0.1.2.dist-info/licenses/LICENSE
filedeletemanager/__init__.py
filedeletemanager/cli.py
filedeletemanager/core.py
filedeletemanager/rules.py
filedeletemanager/utils.py
file_delete_manager-0.1.2.dist-info/METADATA
file_delete_manager-0.1.2.dist-info/WHEEL
file_delete_manager-0.1.2.dist-info/entry_points.txt
file_delete_manager-0.1.2.dist-info/top_level.txt
file_delete_manager-0.1.2.dist-info/RECORD
