Metadata-Version: 2.4
Name: file_delete_manager
Version: 0.1.2
Summary: Library to delete files with rules
Author: Juan Manuel Cabrera
License: MIT
Requires-Python: >=3.8
License-File: LICENSE
Dynamic: license-file
